[{"CreateDate": "/Date(1488203384000+0100)/", "DeliveryMethodTypeCode": null, "DeliveryName": null, "EditDate": "/Date(1526966698000+0200)/", "HasSampleComment": false, "IndexFlagCodes": null, "IndexValues": [], "IsBiologicalSample": false, "LocationX": "576735", "LocationY": "6538653", "MaxDepth": "0,5", "MinDepth": "0,5", "NumSubSamples": null, "ObservationValues": [{"AccessRestriction": 0, "AnalysisDate": "/Date(1479682800000+0100)/", "AnalysisLab": "SLUVoM", "AnalysisMethod": "SS-EN ISO 7887-2012", "DefaultUnitName": "/5cm", "DefaultValue": "2,242", "IsAccredited": true, "IsComplexType": false, "IsQualitative": false, "ObservationSetId": 556476, "ObservedPropertyId": 11586533, "PropertyAbbrevName": "Abs_F 254", "PropertyAuthorityCode": "Default", "PropertyCode": "Abs_F254", "PropertyName": "Absorbans filtrerat (254 nm)", "QualityCode": "A", "ReportedValue": "2,242", "TaxonSwedishName": null, "UnitOfMeasureId": 35, "UnitOfMeasureName": "/5cm", "ValueRepresentationTypeName": "NumericProperty"}, {"AccessRestriction": 0, "AnalysisDate": "/Date(1479682800000+0100)/", "AnalysisLab": "SLUVoM", "AnalysisMethod": "SS-EN ISO 7887-2012", "DefaultUnitName": "/5cm", "DefaultValue": "0,278", "IsAccredited": true, "IsComplexType": false, "IsQualitative": false, "ObservationSetId": 556476, "ObservedPropertyId": 11586534, "PropertyAbbrevName": "Abs_F 365", "PropertyAuthorityCode": "Default", "PropertyCode": "Abs_F365", "PropertyName": "Absorbans filtrerat (365 nm)", "QualityCode": "A", "ReportedValue": "0,278", "TaxonSwedishName": null, "UnitOfMeasureId": 35, "UnitOfMeasureName": "/5cm", "ValueRepresentationTypeName": "NumericProperty"}, {"AccessRestriction": 0, "AnalysisDate": "/Date(1479682800000+0100)/", "AnalysisLab": "SLUVoM", "AnalysisMethod": "SS-EN ISO 7887-2012", "DefaultUnitName": "/5cm", "DefaultValue": "0,092", "IsAccredited": true, "IsComplexType": false, "IsQualitative": false, "ObservationSetId": 556476, "ObservedPropertyId": 11586535, "PropertyAbbrevName": "Abs_F 420", "PropertyAuthorityCode": "Default", "PropertyCode": "Abs_F420", "PropertyName": "Absorbans filtrerat (420 nm)", "QualityCode": "A", "ReportedValue": "0,092", "TaxonSwedishName": null, "UnitOfMeasureId": 35, "UnitOfMeasureName": "/5cm", "ValueRepresentationTypeName": "NumericProperty"}, {"AccessRestriction": 0, "AnalysisDate": "/Date(1479682800000+0100)/", "AnalysisLab": "SLUVoM", "AnalysisMethod": "SS-EN ISO 7887-2012", "DefaultUnitName": "/m", "DefaultValue": "1,4", "IsAccredited": true, "IsComplexType": false, "IsQualitative": false, "ObservationSetId": 556476, "ObservedPropertyId": 11586532, "PropertyAbbrevName": "Abs_F 436", "PropertyAuthorityCode": "Default", "PropertyCode": "Abs_436m", "PropertyName": "Absorbans filtrerat (436 nm)", "QualityCode": "A", "ReportedValue": "0,069", "TaxonSwedishName": null, "UnitOfMeasureId": 35, "UnitOfMeasureName": "/5cm", "ValueRepresentationTypeName": "NumericProperty"}, {"AccessRestriction": 0, "AnalysisDate": "/Date(1479682800000+0100)/", "AnalysisLab": "SLUVoM", "AnalysisMethod": "SS-EN ISO 9963-2 utg1, mod/St Methods 16th Ed 402", "DefaultUnitName": "mekv/l", "DefaultValue": "0,922", "IsAccredited": true, "IsComplexType": false, "IsQualitative": false, "ObservationSetId": 556476, "ObservedPropertyId": 11586537, "PropertyAbbrevName": "Alk/Acid", "PropertyAuthorityCode": "Default", "PropertyCode": "Alk_Acid", "PropertyName": "Alkalinitet/Acid.", "QualityCode": "A", "ReportedValue": "0,922", "TaxonSwedishName": null, "UnitOfMeasureId": 7, "UnitOfMeasureName": "mekv/l", "ValueRepresentationTypeName": "NumericProperty"}, {"AccessRestriction": 0, "AnalysisDate": "/Date(1480374000000+0100)/", "AnalysisLab": "SLUVoM", "AnalysisMethod": "SS-EN ISO 17294-2:2016", "DefaultUnitName": "\u00b5g/l", "DefaultValue": "110", "IsAccredited": true, "IsComplexType": false, "IsQualitative": false, "ObservationSetId": 556476, "ObservedPropertyId": 11586536, "PropertyAbbrevName": "Al", "PropertyAuthorityCode": "Default", "PropertyCode": "Al", "PropertyName": "Aluminium", "QualityCode": "A", "ReportedValue": "110", "TaxonSwedishName": null, "UnitOfMeasureId": 2, "UnitOfMeasureName": "\u00b5g/l", "ValueRepresentationTypeName": "NumericProperty"}, {"AccessRestriction": 0, "AnalysisDate": "/Date(1479682800000+0100)/", "AnalysisLab": "SLUVoM", "AnalysisMethod": "ISO/FDIS 15923-1", "DefaultUnitName": "\u00b5g/l N", "DefaultValue": "549", "IsAccredited": true, "IsComplexType": false, "IsQualitative": false, "ObservationSetId": 556476, "ObservedPropertyId": 11586552, "PropertyAbbrevName": "NH4-N", "PropertyAuthorityCode": "Default", "PropertyCode": "NH4_N", "PropertyName": "Ammoniumkv\u00e4ve", "QualityCode": "A", "ReportedValue": "549", "TaxonSwedishName": null, "UnitOfMeasureId": 2, "UnitOfMeasureName": "\u00b5g/l", "ValueRepresentationTypeName": "NumericProperty"}, {"AccessRestriction": 0, "AnalysisDate": "/Date(1480374000000+0100)/", "AnalysisLab": "SLUVoM", "AnalysisMethod": "SS-EN ISO 17294-2:2016", "DefaultUnitName": "\u00b5g/l", "DefaultValue": "0,65", "IsAccredited": true, "IsComplexType": false, "IsQualitative": false, "ObservationSetId": 556476, "ObservedPropertyId": 11586538, "PropertyAbbrevName": "As", "PropertyAuthorityCode": "Default", "PropertyCode": "As", "PropertyName": "Arsenik", "QualityCode": "A", "ReportedValue": "0,65", "TaxonSwedishName": null, "UnitOfMeasureId": 2, "UnitOfMeasureName": "\u00b5g/l", "ValueRepresentationTypeName": "NumericProperty"}, {"AccessRestriction": 0, "AnalysisDate": "/Date(1480374000000+0100)/", "AnalysisLab": "SLUVoM", "AnalysisMethod": "SS-EN ISO 17294-2:2016", "DefaultUnitName": "\u00b5g/l", "DefaultValue": "0,29", "IsAccredited": true, "IsComplexType": false, "IsQualitative": false, "ObservationSetId": 556476, "ObservedPropertyId": 11586555, "PropertyAbbrevName": "Pb", "PropertyAuthorityCode": "Default", "PropertyCode": "Pb", "PropertyName": "Bly", "QualityCode": "A", "ReportedValue": "0,29", "TaxonSwedishName": null, "UnitOfMeasureId": 2, "UnitOfMeasureName": "\u00b5g/l", "ValueRepresentationTypeName": "NumericProperty"}, {"AccessRestriction": 0, "AnalysisDate": "/Date(1482274800000+0100)/", "AnalysisLab": "SLUVoM", "AnalysisMethod": "SS-EN ISO 10 304-1:2009, mod.", "DefaultUnitName": "mg/l", "DefaultValue": "0,34", "IsAccredited": true, "IsComplexType": false, "IsQualitative": false, "ObservationSetId": 556476, "ObservedPropertyId": 11586546, "PropertyAbbrevName": "F", "PropertyAuthorityCode": "Default", "PropertyCode": "Fluorid", "PropertyName": "Fluorid", "QualityCode": "A", "ReportedValue": "0,34", "TaxonSwedishName": null, "UnitOfMeasureId": 8, "UnitOfMeasureName": "mg/l", "ValueRepresentationTypeName": "NumericProperty"}, {"AccessRestriction": 0, "AnalysisDate": "/Date(1479682800000+0100)/", "AnalysisLab": "SLUVoM", "AnalysisMethod": "ISO/FDIS 15923-1", "DefaultUnitName": "\u00b5g/l P", "DefaultValue": "13", "IsAccredited": true, "IsComplexType": false, "IsQualitative": false, "ObservationSetId": 556476, "ObservedPropertyId": 11586557, "PropertyAbbrevName": "PO4-P", "PropertyAuthorityCode": "Default", "PropertyCode": "PO4_P", "PropertyName": "Fosfatfosfor", "QualityCode": "A", "ReportedValue": "13", "TaxonSwedishName": null, "UnitOfMeasureId": 2, "UnitOfMeasureName": "\u00b5g/l", "ValueRepresentationTypeName": "NumericProperty"}, {"AccessRestriction": 0, "AnalysisDate": "/Date(1480374000000+0100)/", "AnalysisLab": "SLUVoM", "AnalysisMethod": "SS-EN ISO 17294-2:2016", "DefaultUnitName": "\u00b5g/l", "DefaultValue": "420", "IsAccredited": true, "IsComplexType": false, "IsQualitative": false, "ObservationSetId": 556476, "ObservedPropertyId": 11586545, "PropertyAbbrevName": "Fe", "PropertyAuthorityCode": "Default", "PropertyCode": "Fe", "PropertyName": "J\u00e4rn", "QualityCode": "A", "ReportedValue": "420", "TaxonSwedishName": null, "UnitOfMeasureId": 2, "UnitOfMeasureName": "\u00b5g/l", "ValueRepresentationTypeName": "NumericProperty"}, {"AccessRestriction": 0, "AnalysisDate": "/Date(1480374000000+0100)/", "AnalysisLab": "SLUVoM", "AnalysisMethod": "SS-EN ISO 17294-2:2016", "DefaultUnitName": "\u00b5g/l", "DefaultValue": "0,007", "IsAccredited": true, "IsComplexType": false, "IsQualitative": false, "ObservationSetId": 556476, "ObservedPropertyId": 11586540, "PropertyAbbrevName": "Cd", "PropertyAuthorityCode": "Default", "PropertyCode": "Cd", "PropertyName": "Kadmium", "QualityCode": "A", "ReportedValue": "0,007", "TaxonSwedishName": null, "UnitOfMeasureId": 2, "UnitOfMeasureName": "\u00b5g/l", "ValueRepresentationTypeName": "NumericProperty"}, {"AccessRestriction": 0, "AnalysisDate": "/Date(1480374000000+0100)/", "AnalysisLab": "SLUVoM", "AnalysisMethod": "SS-EN ISO 17294-2:2016", "DefaultUnitName": "mg/l", "DefaultValue": "18", "IsAccredited": true, "IsComplexType": false, "IsQualitative": false, "ObservationSetId": 556476, "ObservedPropertyId": 11586539, "PropertyAbbrevName": "Ca", "PropertyAuthorityCode": "Default", "PropertyCode": "Ca", "PropertyName": "Kalcium", "QualityCode": "A", "ReportedValue": "18", "TaxonSwedishName": null, "UnitOfMeasureId": 8, "UnitOfMeasureName": "mg/l", "ValueRepresentationTypeName": "NumericProperty"}, {"AccessRestriction": 0, "AnalysisDate": "/Date(1480374000000+0100)/", "AnalysisLab": "SLUVoM", "AnalysisMethod": "SS-EN ISO 17294-2:2016", "DefaultUnitName": "mg/l", "DefaultValue": "2,4", "IsAccredited": true, "IsComplexType": false, "IsQualitative": false, "ObservationSetId": 556476, "ObservedPropertyId": 11586547, "PropertyAbbrevName": "K", "PropertyAuthorityCode": "Default", "PropertyCode": "K", "PropertyName": "Kalium", "QualityCode": "A", "ReportedValue": "2,4", "TaxonSwedishName": null, "UnitOfMeasureId": 8, "UnitOfMeasureName": "mg/l", "ValueRepresentationTypeName": "NumericProperty"}, {"AccessRestriction": 0, "AnalysisDate": "/Date(1480374000000+0100)/", "AnalysisLab": "SLUVoM", "AnalysisMethod": "SS-EN ISO 17294-2:2016", "DefaultUnitName": "mg/l", "DefaultValue": "1,2", "IsAccredited": true, "IsComplexType": false, "IsQualitative": false, "ObservationSetId": 556476, "ObservedPropertyId": 11586558, "PropertyAbbrevName": "Si", "PropertyAuthorityCode": "Default", "PropertyCode": "Si", "PropertyName": "Kisel", "QualityCode": "A", "ReportedValue": "1,2", "TaxonSwedishName": null, "UnitOfMeasureId": 8, "UnitOfMeasureName": "mg/l", "ValueRepresentationTypeName": "NumericProperty"}, {"AccessRestriction": 0, "AnalysisDate": "/Date(1482274800000+0100)/", "AnalysisLab": "SLUVoM", "AnalysisMethod": "SS-EN ISO 10 304-1:2009, mod.", "DefaultUnitName": "mg/l", "DefaultValue": "10", "IsAccredited": true, "IsComplexType": false, "IsQualitative": false, "ObservationSetId": 556476, "ObservedPropertyId": 11586541, "PropertyAbbrevName": "Cl", "PropertyAuthorityCode": "Default", "PropertyCode": "Cl", "PropertyName": "Klorid", "QualityCode": "A", "ReportedValue": "10", "TaxonSwedishName": null, "UnitOfMeasureId": 8, "UnitOfMeasureName": "mg/l", "ValueRepresentationTypeName": "NumericProperty"}, {"AccessRestriction": 0, "AnalysisDate": "/Date(1480374000000+0100)/", "AnalysisLab": "SLUVoM", "AnalysisMethod": "SS-EN ISO 17294-2:2016", "DefaultUnitName": "\u00b5g/l", "DefaultValue": "0,10", "IsAccredited": true, "IsComplexType": false, "IsQualitative": false, "ObservationSetId": 556476, "ObservedPropertyId": 11586542, "PropertyAbbrevName": "Co", "PropertyAuthorityCode": "Default", "PropertyCode": "Co", "PropertyName": "Kobolt", "QualityCode": "A", "ReportedValue": "0,10", "TaxonSwedishName": null, "UnitOfMeasureId": 2, "UnitOfMeasureName": "\u00b5g/l", "ValueRepresentationTypeName": "NumericProperty"}, {"AccessRestriction": 0, "AnalysisDate": "/Date(1479682800000+0100)/", "AnalysisLab": "SLUVoM", "AnalysisMethod": "SS-EN 27888, utg 1", "DefaultUnitName": "mS/m", "DefaultValue": "17,0", "IsAccredited": true, "IsComplexType": false, "IsQualitative": false, "ObservationSetId": 556476, "ObservedPropertyId": 11586548, "PropertyAbbrevName": "Kond_25", "PropertyAuthorityCode": "Default", "PropertyCode": "Kond_25", "PropertyName": "Konduktivitet 25\u00b0", "QualityCode": "A", "ReportedValue": "17,0", "TaxonSwedishName": null, "UnitOfMeasureId": 11, "UnitOfMeasureName": "mS/m", "ValueRepresentationTypeName": "NumericProperty"}, {"AccessRestriction": 0, "AnalysisDate": "/Date(1480374000000+0100)/", "AnalysisLab": "SLUVoM", "AnalysisMethod": "SS-EN ISO 17294-2:2016", "DefaultUnitName": "\u00b5g/l", "DefaultValue": "0,57", "IsAccredited": true, "IsComplexType": false, "IsQualitative": false, "ObservationSetId": 556476, "ObservedPropertyId": 11586544, "PropertyAbbrevName": "Cu", "PropertyAuthorityCode": "Default", "PropertyCode": "Cu", "PropertyName": "Koppar", "QualityCode": "A", "ReportedValue": "0,57", "TaxonSwedishName": null, "UnitOfMeasureId": 2, "UnitOfMeasureName": "\u00b5g/l", "ValueRepresentationTypeName": "NumericProperty"}, {"AccessRestriction": 0, "AnalysisDate": "/Date(1480374000000+0100)/", "AnalysisLab": "SLUVoM", "AnalysisMethod": "SS-EN ISO 17294-2:2016", "DefaultUnitName": "\u00b5g/l", "DefaultValue": "0,14", "IsAccredited": true, "IsComplexType": false, "IsQualitative": false, "ObservationSetId": 556476, "ObservedPropertyId": 11586543, "PropertyAbbrevName": "Cr", "PropertyAuthorityCode": "Default", "PropertyCode": "Cr", "PropertyName": "Krom", "QualityCode": "A", "ReportedValue": "0,14", "TaxonSwedishName": null, "UnitOfMeasureId": 2, "UnitOfMeasureName": "\u00b5g/l", "ValueRepresentationTypeName": "NumericProperty"}, {"AccessRestriction": 0, "AnalysisDate": "/Date(1480374000000+0100)/", "AnalysisLab": "SLUVoM", "AnalysisMethod": "SS-EN ISO 17294-2:2016", "DefaultUnitName": "mg/l", "DefaultValue": "4,4", "IsAccredited": true, "IsComplexType": false, "IsQualitative": false, "ObservationSetId": 556476, "ObservedPropertyId": 11586549, "PropertyAbbrevName": "Mg", "PropertyAuthorityCode": "Default", "PropertyCode": "Mg", "PropertyName": "Magnesium", "QualityCode": "A", "ReportedValue": "4,4", "TaxonSwedishName": null, "UnitOfMeasureId": 8, "UnitOfMeasureName": "mg/l", "ValueRepresentationTypeName": "NumericProperty"}, {"AccessRestriction": 0, "AnalysisDate": "/Date(1480374000000+0100)/", "AnalysisLab": "SLUVoM", "AnalysisMethod": "SS-EN ISO 17294-2:2016", "DefaultUnitName": "\u00b5g/l", "DefaultValue": "54", "IsAccredited": true, "IsComplexType": false, "IsQualitative": false, "ObservationSetId": 556476, "ObservedPropertyId": 11586550, "PropertyAbbrevName": "Mn", "PropertyAuthorityCode": "Default", "PropertyCode": "Mn", "PropertyName": "Mangan", "QualityCode": "A", "ReportedValue": "54", "TaxonSwedishName": null, "UnitOfMeasureId": 2, "UnitOfMeasureName": "\u00b5g/l", "ValueRepresentationTypeName": "NumericProperty"}, {"AccessRestriction": 0, "AnalysisDate": "/Date(1480374000000+0100)/", "AnalysisLab": "SLUVoM", "AnalysisMethod": "SS-EN ISO 17294-2:2016", "DefaultUnitName": "mg/l", "DefaultValue": "7,7", "IsAccredited": true, "IsComplexType": false, "IsQualitative": false, "ObservationSetId": 556476, "ObservedPropertyId": 11586551, "PropertyAbbrevName": "Na", "PropertyAuthorityCode": "Default", "PropertyCode": "Na", "PropertyName": "Natrium", "QualityCode": "A", "ReportedValue": "7,7", "TaxonSwedishName": null, "UnitOfMeasureId": 8, "UnitOfMeasureName": "mg/l", "ValueRepresentationTypeName": "NumericProperty"}, {"AccessRestriction": 0, "AnalysisDate": "/Date(1480374000000+0100)/", "AnalysisLab": "SLUVoM", "AnalysisMethod": "SS-EN ISO 17294-2:2016", "DefaultUnitName": "\u00b5g/l", "DefaultValue": "0,44", "IsAccredited": true, "IsComplexType": false, "IsQualitative": false, "ObservationSetId": 556476, "ObservedPropertyId": 11586553, "PropertyAbbrevName": "Ni", "PropertyAuthorityCode": "Default", "PropertyCode": "Ni", "PropertyName": "Nickel", "QualityCode": "A", "ReportedValue": "0,44", "TaxonSwedishName": null, "UnitOfMeasureId": 2, "UnitOfMeasureName": "\u00b5g/l", "ValueRepresentationTypeName": "NumericProperty"}, {"AccessRestriction": 0, "AnalysisDate": "/Date(1479682800000+0100)/", "AnalysisLab": "SLUVoM", "AnalysisMethod": "ISO/FDIS 15923-1", "DefaultUnitName": "\u00b5g/l N", "DefaultValue": "58", "IsAccredited": true, "IsComplexType": false, "IsQualitative": false, "ObservationSetId": 556476, "ObservedPropertyId": 11586554, "PropertyAbbrevName": "NO2+NO3-N", "PropertyAuthorityCode": "Default", "PropertyCode": "NO2_NO3_N", "PropertyName": "Nitrit+Nitratkv\u00e4ve", "QualityCode": "A", "ReportedValue": "58", "TaxonSwedishName": null, "UnitOfMeasureId": 2, "UnitOfMeasureName": "\u00b5g/l", "ValueRepresentationTypeName": "NumericProperty"}, {"AccessRestriction": 0, "AnalysisDate": "/Date(1479682800000+0100)/", "AnalysisLab": "SLUVoM", "AnalysisMethod": "SS 02 81 22, utg, 2, mod.", "DefaultUnitName": null, "DefaultValue": "7,21", "IsAccredited": true, "IsComplexType": false, "IsQualitative": false, "ObservationSetId": 556476, "ObservedPropertyId": 11586556, "PropertyAbbrevName": "pH", "PropertyAuthorityCode": "Default", "PropertyCode": "pH", "PropertyName": "pH", "QualityCode": "A", "ReportedValue": "7,21", "TaxonSwedishName": null, "UnitOfMeasureId": null, "UnitOfMeasureName": null, "ValueRepresentationTypeName": "NumericProperty"}, {"AccessRestriction": 0, "AnalysisDate": "/Date(1480374000000+0100)/", "AnalysisLab": "SLUVoM", "AnalysisMethod": "SS-EN ISO 17294-2:2016", "DefaultUnitName": "\u00b5g/l", "DefaultValue": "54", "IsAccredited": true, "IsComplexType": false, "IsQualitative": false, "ObservationSetId": 556476, "ObservedPropertyId": 11586560, "PropertyAbbrevName": "Sr", "PropertyAuthorityCode": "Default", "PropertyCode": "Sr", "PropertyName": "Strontium", "QualityCode": "A", "ReportedValue": "54", "TaxonSwedishName": null, "UnitOfMeasureId": 2, "UnitOfMeasureName": "\u00b5g/l", "ValueRepresentationTypeName": "NumericProperty"}, {"AccessRestriction": 0, "AnalysisDate": "/Date(1482274800000+0100)/", "AnalysisLab": "SLUVoM", "AnalysisMethod": "SS-EN ISO 10 304-1:2009, mod.", "DefaultUnitName": "mg/l", "DefaultValue": "15", "IsAccredited": true, "IsComplexType": false, "IsQualitative": false, "ObservationSetId": 556476, "ObservedPropertyId": 11586559, "PropertyAbbrevName": "SO4_IC", "PropertyAuthorityCode": "Default", "PropertyCode": "SO4_IC", "PropertyName": "Sulfat(IC)", "QualityCode": "A", "ReportedValue": "15", "TaxonSwedishName": null, "UnitOfMeasureId": 8, "UnitOfMeasureName": "mg/l", "ValueRepresentationTypeName": "NumericProperty"}, {"AccessRestriction": 0, "AnalysisDate": "/Date(1479682800000+0100)/", "AnalysisLab": "SLUVoM", "AnalysisMethod": "SS-EN 1484, utg. 1", "DefaultUnitName": "mg/l C", "DefaultValue": "22,5", "IsAccredited": true, "IsComplexType": false, "IsQualitative": false, "ObservationSetId": 556476, "ObservedPropertyId": 11586562, "PropertyAbbrevName": "TOC", "PropertyAuthorityCode": "Default", "PropertyCode": "TOC", "PropertyName": "Tot. org. kol TOC", "QualityCode": "A", "ReportedValue": "22,5", "TaxonSwedishName": null, "UnitOfMeasureId": 8, "UnitOfMeasureName": "mg/l", "ValueRepresentationTypeName": "NumericProperty"}, {"AccessRestriction": 0, "AnalysisDate": "/Date(1483570800000+0100)/", "AnalysisLab": "SLUVoM", "AnalysisMethod": "SS-EN ISO 6878:2005, mod. Bran Luebbe, M. G-175-96", "DefaultUnitName": "\u00b5g/l P", "DefaultValue": "81,3", "IsAccredited": true, "IsComplexType": false, "IsQualitative": false, "ObservationSetId": 556476, "ObservedPropertyId": 11586564, "PropertyAbbrevName": "Tot-P", "PropertyAuthorityCode": "Default", "PropertyCode": "Tot_P", "PropertyName": "Totalfosfor", "QualityCode": "A", "ReportedValue": "81,3", "TaxonSwedishName": null, "UnitOfMeasureId": 2, "UnitOfMeasureName": "\u00b5g/l", "ValueRepresentationTypeName": "NumericProperty"}, {"AccessRestriction": 0, "AnalysisDate": "/Date(1479682800000+0100)/", "AnalysisLab": "SLUVoM", "AnalysisMethod": "SS-EN 12260:2004", "DefaultUnitName": "\u00b5g/l N", "DefaultValue": "2070", "IsAccredited": true, "IsComplexType": false, "IsQualitative": false, "ObservationSetId": 556476, "ObservedPropertyId": 11586563, "PropertyAbbrevName": "Tot-N_TNb", "PropertyAuthorityCode": "Default", "PropertyCode": "Tot_N_TNb", "PropertyName": "Tot-N(TNb)", "QualityCode": "A", "ReportedValue": "2070", "TaxonSwedishName": null, "UnitOfMeasureId": 2, "UnitOfMeasureName": "\u00b5g/l", "ValueRepresentationTypeName": "NumericProperty"}, {"AccessRestriction": 0, "AnalysisDate": "/Date(1479682800000+0100)/", "AnalysisLab": "SLUVoM", "AnalysisMethod": "SS-EN ISO 7027, utg. 1", "DefaultUnitName": "FNU", "DefaultValue": "5,7", "IsAccredited": true, "IsComplexType": false, "IsQualitative": false, "ObservationSetId": 556476, "ObservedPropertyId": 11586565, "PropertyAbbrevName": "Turb_FNU", "PropertyAuthorityCode": "Default", "PropertyCode": "Turb_FNU", "PropertyName": "Turbiditet FNU", "QualityCode": "A", "ReportedValue": "5,7", "TaxonSwedishName": null, "UnitOfMeasureId": 25, "UnitOfMeasureName": "FNU", "ValueRepresentationTypeName": "NumericProperty"}, {"AccessRestriction": 0, "AnalysisDate": "/Date(1480374000000+0100)/", "AnalysisLab": "SLUVoM", "AnalysisMethod": "SS-EN ISO 17294-2:2016", "DefaultUnitName": "\u00b5g/l", "DefaultValue": "0,28", "IsAccredited": true, "IsComplexType": false, "IsQualitative": false, "ObservationSetId": 556476, "ObservedPropertyId": 11586566, "PropertyAbbrevName": "U", "PropertyAuthorityCode": "Default", "PropertyCode": "U", "PropertyName": "Uran", "QualityCode": "A", "ReportedValue": "0,28", "TaxonSwedishName": null, "UnitOfMeasureId": 2, "UnitOfMeasureName": "\u00b5g/l", "ValueRepresentationTypeName": "NumericProperty"}, {"AccessRestriction": 0, "AnalysisDate": "/Date(1480374000000+0100)/", "AnalysisLab": "SLUVoM", "AnalysisMethod": "SS-EN ISO 17294-2:2016", "DefaultUnitName": "\u00b5g/l", "DefaultValue": "0,56", "IsAccredited": true, "IsComplexType": false, "IsQualitative": false, "ObservationSetId": 556476, "ObservedPropertyId": 11586567, "PropertyAbbrevName": "V", "PropertyAuthorityCode": "Default", "PropertyCode": "V", "PropertyName": "Vanadin", "QualityCode": "A", "ReportedValue": "0,56", "TaxonSwedishName": null, "UnitOfMeasureId": 2, "UnitOfMeasureName": "\u00b5g/l", "ValueRepresentationTypeName": "NumericProperty"}, {"AccessRestriction": 0, "AnalysisDate": "/Date(1479596400000+0100)/", "AnalysisLab": "SLUVoM", "AnalysisMethod": null, "DefaultUnitName": "\u00b0C", "DefaultValue": "1,8", "IsAccredited": false, "IsComplexType": false, "IsQualitative": false, "ObservationSetId": 556476, "ObservedPropertyId": 11586561, "PropertyAbbrevName": "Vattentemperatur", "PropertyAuthorityCode": "Default", "PropertyCode": "Temp", "PropertyName": "Vattentemperatur", "QualityCode": "A", "ReportedValue": "1,8", "TaxonSwedishName": null, "UnitOfMeasureId": 1, "UnitOfMeasureName": "\u00b0C", "ValueRepresentationTypeName": "NumericProperty"}, {"AccessRestriction": 0, "AnalysisDate": "/Date(1480374000000+0100)/", "AnalysisLab": "SLUVoM", "AnalysisMethod": "SS-EN ISO 17294-2:2016", "DefaultUnitName": "\u00b5g/l", "DefaultValue": "1,4", "IsAccredited": true, "IsComplexType": false, "IsQualitative": false, "ObservationSetId": 556476, "ObservedPropertyId": 11586568, "PropertyAbbrevName": "Zn", "PropertyAuthorityCode": "Default", "PropertyCode": "Zn", "PropertyName": "Zink", "QualityCode": "A", "ReportedValue": "1,4", "TaxonSwedishName": null, "UnitOfMeasureId": 2, "UnitOfMeasureName": "\u00b5g/l", "ValueRepresentationTypeName": "NumericProperty"}], "ObservedPropertyList": [], "ProductCode": "Vnk", "ProductName": "Vattenkemi", "RelativeLocationType": 10, "SampleAccredited": "Ackrediterat, Ej ackrediterat", "SampleAnalysisLab": "SLUVoM", "SampleAnalysisMethod": "SS-EN ISO 7887-2012, SS-EN ISO 9963-2 utg1, mod/St Methods 16th Ed 402, SS-EN ISO 17294-2:2016, ISO/FDIS 15923-1, SS-EN ISO 10 304-1:2009, mod., SS-EN 27888, utg 1, SS 02 81 22, utg, 2, mod., SS-EN 1484, utg. 1, SS-EN ISO 6878:2005, mod. Bran Luebbe, M. G-175-96, SS-EN 12260:2004, SS-EN ISO 7027, utg. 1", "SampleCommentFirst100": null, "SampleCoordinate": null, "SampleCoordinateSRS": null, "SampleDate": "/Date(1479596400000+0100)/", "SampleId": 556476, "SampleIsSensitive": false, "SampleLocationWkt": null, "SampleMediumTypeName": "Sj\u00f6", "SampleMetadataList": [], "SampleStatus": "Authorized", "SamplingMethod": null, "SamplingMethodStandard": null, "SamplingMethodTypeCode": null, "SiteCoordinate": null, "SiteEUId": null, "SiteId": 35990, "SiteMetadata": [], "SiteName": "Stensj\u00f6n", "SiteType": "Sj\u00f6", "SourceSampleId": "LIMS-Sample_207444", "StudyName": "Sj\u00f6ar omdrevsstationer", "SubProgramName": "NM\u00d6", "SurveyType": null, "TaxonGroupCalculationValues": [], "UserIsAuthorized": false, "WaterZone": null}]